roamPy/__init__.py
roamPy/heartbeatClass.py
roamPy/licensesClass.py
roamPy/pageFunc.py
roamPy/productsClass.py
roamPy/roamClass.py
roamPy/subscriptionPeriodsClass.py
roamPy/subscriptionsClass.py
roamPy-0.1.4.dist-info/LICENSE
roamPy-0.1.4.dist-info/METADATA
roamPy-0.1.4.dist-info/WHEEL
roamPy-0.1.4.dist-info/top_level.txt
roamPy-0.1.4.dist-info/RECORD
