Metadata-Version: 2.1
Name: roamPy
Version: 0.1.4
Summary: API wrapper class for roam.plus
Home-page: https://roamPy.readthedocs.io/
Author: Matthew Hutchinson
Author-email: maahutch@stanford.edu
License: MIT
Platform: UNKNOWN
Classifier: Intended Audience :: Developers
Classifier: License :: OSI Approved :: MIT License
Classifier: Programming Language :: Python
Classifier: Programming Language :: Python :: 3
Classifier: Programming Language :: Python :: 3.6
Classifier: Programming Language :: Python :: 3.7
Classifier: Programming Language :: Python :: 3.8
Classifier: Programming Language :: Python :: 3.9
Classifier: Operating System :: OS Independent
License-File: LICENSE
Requires-Dist: requests
